OHDLF_pro/__init__.py
OHDLF_pro/_main_.py
OHDLF_pro/main.py
OHDLF_pro/utils/__init__.py
OHDLF_pro/utils/disco.py
ohdlf_pro-1.0.0.dist-info/LICENSE
ohdlf_pro-1.0.0.dist-info/METADATA
ohdlf_pro-1.0.0.dist-info/WHEEL
ohdlf_pro-1.0.0.dist-info/entry_points.txt
ohdlf_pro-1.0.0.dist-info/top_level.txt
ohdlf_pro-1.0.0.dist-info/RECORD
