Metadata-Version: 2.1
Name: ohdlf-pro
Version: 1.0.0
Summary: OHDLF-pro: a pipeline designed to filter and address orthologous gene heterogeneity, duplication, and loss
Home-page: https://github.com/qunjie-zhang/OHDLF-pro
Author: ['caijunhao']
Author-email: cjunhao416@gmail.com
Keywords: Phylogenetic,bioinformatics,pipeline
Classifier: Development Status :: 5 - Production/Stable
Classifier: License :: OSI Approved :: Apache Software License
Classifier: Operating System :: OS Independent
Classifier: Programming Language :: Python :: 3.5
Classifier: Programming Language :: Python :: 3.6
Classifier: Programming Language :: Python :: 3.7
Classifier: Programming Language :: Python :: 3.8
Classifier: Programming Language :: Python :: 3.9
Classifier: Programming Language :: Python :: 3.10
Classifier: Programming Language :: Python :: 3.11
Requires-Python: >=3.5
License-File: LICENSE
Requires-Dist: biopython
Requires-Dist: tqdm
Requires-Dist: treeswift
Requires-Dist: importlib-metadata ; python_version < "3.8"
